README.md
setup.py
converttentotwenty/__init__.py
converttentotwenty/converttentotwenty.py
converttentotwenty.egg-info/PKG-INFO
converttentotwenty.egg-info/SOURCES.txt
converttentotwenty.egg-info/dependency_links.txt
converttentotwenty.egg-info/top_level.txt