Metadata-Version: 2.1
Name: converttentotwenty
Version: 3.0.1
Summary: Ma bibliothèque Python
Home-page: https://github.com/Joris-ROBIN/Converttentotwenty.git
Author: Skairipa
Author-email: jorisrobin34@gmail.com
License: MEEF
Classifier: Programming Language :: Python :: 3
Classifier: License :: OSI Approved :: GNU General Public License v2 (GPLv2)
Classifier: Operating System :: OS Independent
